robertsons_rules/__init__.py
robertsons_rules/plotting.py
robertsons_rules/fonts/LICENSE.txt
robertsons_rules/fonts/Roboto-Regular.ttf
robertsons_rules-0.1.2.dist-info/LICENSE.md
robertsons_rules-0.1.2.dist-info/METADATA
robertsons_rules-0.1.2.dist-info/WHEEL
robertsons_rules-0.1.2.dist-info/top_level.txt
robertsons_rules-0.1.2.dist-info/RECORD
